yapq/__init__.py
yapq/job.py
yapq/result.py
yapq/serializer.py
yapq/task_registry.py
yapq/worker.py
yapq-0.4.0.dist-info/AUTHORS.rst
yapq-0.4.0.dist-info/LICENSE
yapq-0.4.0.dist-info/METADATA
yapq-0.4.0.dist-info/WHEEL
yapq-0.4.0.dist-info/top_level.txt
yapq-0.4.0.dist-info/RECORD
