Metadata-Version: 2.1
Name: yapq
Version: 0.4.0
Summary: Yet Another Python Queue
Home-page: https://github.com/ginkooo/yapq
Author: Piotr Czajka
Author-email: czajka@protonmail.com
License: MIT license
Keywords: yapq
Platform: UNKNOWN
Classifier: Development Status :: 2 - Pre-Alpha
Classifier: Intended Audience :: Developers
Classifier: License :: OSI Approved :: MIT License
Classifier: Natural Language :: English
Classifier: Programming Language :: Python :: 2
Classifier: Programming Language :: Python :: 2.7
Classifier: Programming Language :: Python :: 3
Classifier: Programming Language :: Python :: 3.5
Classifier: Programming Language :: Python :: 3.6
Classifier: Programming Language :: Python :: 3.7
Classifier: Programming Language :: Python :: 3.8
Requires-Python: >=3.6
